{
  "url": "http://english.sina.com/sports/2012/0810/495416.html",
  "title": "Chinese diver determined to bag seventh diving gold",
  "pubdate": "2012-08-11 01:32:26 GMT",
  "description": "LONDON， Aug. 10 (Xinhua) -- China\u0026#39;s diving world champion Qiu Bo launched a near-perfect display from the 10m platform on Friday to qualify in top spot for Saturday\u0026#39;s semifinals.",
  "cleanContent": "LONDON, Aug. 10 (Xinhua) -- China\u0027s diving world champion Qiu Bo launched a near-perfect display from the 10m platform on Friday to qualify in top spot for Saturday\u0027s semifinals.Qiu, winner of the event at the 2011 World Championships, led the field with the highest 563.70 points, more than 30 points ahead of his teammate Lin Yue who ended second with 532.15 points.Germany\u0027s Sascha Kelin, bronze medallist of the Shanghai World Championships, dived consistently well to finish third.Defending champion Aussie Matthew Mitcham, who struggled with injuries since Beijing Games, looked off his best as he finished ninth.Moreover, British home favourite Tom Daley looked nervous as he started his individual campaign with an indifferent first dive, which was only good enough for 18th after round one.The 18-year-old looked out of form as his penultimate dive only scored 39.60 points, one of the lowest of the night. The score saw Daley drop to 16th before going through in 15th.His teammate Peter Waterfield, silver medallist in the synchro platform at Athens Games, had a poor evening as he finished 23rd and failed to progress.Saturday will see the last gold medal from diving competitions. So far, China has captured six of the seven diving events completed.\t\t\t\t\t\t\t\t\t\t\t\t\t\t\t\t\t\t\t\t\t\t\t\t\t\t\t\t\t\t\t\t\t\t\t\t\t\t\t\t\t\t\t\t\t\t\t\t\t\t\t\t\t\t\t\t\t\t\t\t\t\t\t\t\t\t\t\t\t\t\t\t|  |",
  "type": "sports",
  "pic": "",
  "keywords": "diving:3:1.0;dive:2:0.6362926098452049;points:3:0.6240214730128703;champion:2:0.5197928264648158;platform:2:0.5108689502815005;world:3:0.49763542486794404;games:2:0.48293957190057496;daley:1:0.39148606530053703;tom daley:1:0.39148606530053703;mitcham:1:0.39148606530053703;bo:1:0.3548161851115697;good enough:1:0.33333333333333337;matthew:1:0.33333333333333337;the score:1:0.31814630492260243;23rd:1:0.31814630492260243;18th:1:0.31814630492260243;gold medal:1:0.31814630492260243;of the night:1:0.30630889329186745;bronze:1:0.29656629342137525;the seven:1:0.2883787637082093",
  "topicId": "http://english.sina.com/z/20120628LondonOlympic/index.shtml",
  "imagelist": [
    {
      "url": "http://topnews.in/sports/files/qiu-bo.jpg",
      "title": "Chinese diver determined to bag diving gold at London | TopNews"
    },
    {
      "url": "http://news.xinhuanet.com/english/titlepic/131777286_title1n.jpg",
      "title": "Chinese diver determined to bag seventh diving gold at London ..."
    }
  ],
  "videolist": [
    {
      "url": "http://www.youtube.com/watch?v\u003dc_HpXuWspz8",
      "imgurl": "http://img.youtube.com/vi/c_HpXuWspz8/default.jpg?h\u003d90\u0026w\u003d120\u0026sigh\u003d__dVYIWsAEpmKbTtpEWhLtWI92QnU\u003d",
      "title": "Wu Minxia China\u0026#39;s Won Gold in Women\u0026#39;s 3M ..."
    }
  ]
}