{
  "url": "http://english.sina.com/china/2012/0914/506785.html",
  "title": "Super typhoon Sanba moves closer to China\u0027s Diaoyu Islands",
  "pubdate": "2012-09-15 01:50:27 GMT",
  "description": "BEIJING， Sept. 15 (Xinhua) -- China\u0026#39;s meteorological authority said Saturday the super typhoon Sanba was positioned at waters 750 km southeast of Diaoyu Islands at 5 a.m. and will move closer northward at a speed of 20 kmph.",
  "cleanContent": "BEIJING, Sept. 15 (Xinhua) -- China\u0027s meteorological authority said Saturday the super typhoon Sanba was positioned at waters 750 km southeast of Diaoyu Islands at 5 a.m. and will move closer northward at a speed of 20 kmph.According to forecast by the National Meteorological Center (NMC), typhoon Sanba, the 16th typhoon seen this year, will maintain or slightly weaken its strength before entering waters of the southeastern parts of the East China Sea on Saturday morning.As a result, gales of Beaufort Force 7-9 are forecast in most parts of the East China Sea, the Taiwan Strait, waters east of Taiwan, the estuary of the Yangtze River, the Hangzhou Bay, the southern part of the Yellow Sea and coastal areas in Jiangsu, Zhejiang and Fujian provinces from Saturday morning to Sunday morning.According to the NMC, the super typhoon Sanba will whip up hurricanes at waters near its center as it passes through.Also, the NMC said in its weather forecast that rains will continue in most parts of southwestern China, the southern and eastern part of northwest China and the valley of the Yellow River in Inner Mongolia over the coming three days.\t\t\t\t\t\t\t\t\t\t\t\t\t\t\t\t\t\t\t\t\t\t\t\t\t\t\t\t\t\t\t\t\t\t\t\t\t\t\t\t\t\t\t\t\t\t\t\t\t\t\t\t\t\t\t\t\t\t\t\t\t\t\t\t\t\t\t\t\t\t\t\t|  |",
  "type": "world",
  "pic": "",
  "keywords": "typhoon:4:1.0;the yellow:2:0.639038032969399;forecast:3:0.5912408794809351;the super:2:0.5193226704969608;east:3:0.4061548944269229;china:4:0.35914608741731474;taiwan:2:0.34761479975011234;beaufort:1:0.3195190164846995;yangtze river:1:0.3195190164846995;move closer:1:0.3195190164846995;the valley:1:0.3195190164846995;center:2:0.31637192122186175;whip:1:0.2895901758665899;hurricanes:1:0.2895901758665899;saturday morning:1:0.2596613352484804;bay:1:0.2596613352484804;saturday:2:0.2542710910142711;hangzhou:1:0.2353659737145035;mongolia:1:0.2353659737145035;16th:1:0.22962679521420967",
  "topicId": "http://english.sina.com/z/20120814japanrowneighbor/index.shtml",
  "imagelist": [
    {
      "url": "http://images.china.cn/attachement/jpg/site1007/20120915/001372a9ae0511be43f415.jpg",
      "title": "Super typhoon Sanba moves closer to China\u0026#39;s Diaoyu Islands - China."
    },
    {
      "url": "http://p4.img.cctvpic.com/program/china24/20120916/images/1347760257692_1347760257692_r.jpg",
      "title": "Super typhoon Sanba approaches Diaoyu Islands CCTV News - CNTV English"
    }
  ],
  "videolist": [
    {
      "url": "http://www.youtube.com/watch?v\u003djHCgKkdJ3rc",
      "imgurl": "http://img.youtube.com/vi/jHCgKkdJ3rc/default.jpg?h\u003d90\u0026w\u003d120\u0026sigh\u003d__LrDRpM239Z2ISlOQ_qSbeW4ec5c\u003d",
      "title": "Typhoon Sanba intercept from Okinawa, Japan ..."
    }
  ]
}